coveo_testing/__init__.py
coveo_testing/logging.py
coveo_testing/markers.py
coveo_testing/mocks.py
coveo_testing/parametrize.py
coveo_testing/py.typed
coveo_testing/temporary_resource/__init__.py
coveo_testing/temporary_resource/base.py
coveo_testing/temporary_resource/unique_id.py
coveo_testing-3.0.dist-info/METADATA
coveo_testing-3.0.dist-info/WHEEL
coveo_testing-3.0.dist-info/RECORD
