Metadata-Version: 2.1
Name: coveo-testing
Version: 3.0
Summary: Lightweight testing helpers
Home-page: https://github.com/coveooss/coveo-python-oss/tree/main/coveo-testing
License: Apache-2.0
Author: Jonathan Piché
Author-email: tools@coveo.com
Requires-Python: >=3.9,<4
Classifier: License :: OSI Approved :: Apache Software License
Classifier: Programming Language :: Python :: 3
Classifier: Programming Language :: Python :: 3.9
Classifier: Programming Language :: Python :: 3.10
Classifier: Programming Language :: Python :: 3.11
Requires-Dist: attrs
Requires-Dist: coveo-ref
Requires-Dist: pytest
Project-URL: Repository, https://github.com/coveooss/coveo-python-oss/tree/main/coveo-testing
